metasploitsight/__init__.py
metasploitsight/conf_sample.py
metasploitsight/config.py
metasploitsight/main.py
metasploitsight/monitoring.py
metasploitsight-0.2.0.dist-info/METADATA
metasploitsight-0.2.0.dist-info/WHEEL
metasploitsight-0.2.0.dist-info/entry_points.txt
metasploitsight-0.2.0.dist-info/licenses/COPYING
metasploitsight-0.2.0.dist-info/RECORD
